rpzgen/__init__.py
rpzgen/__main__.py
rpzgen/cli.py
rpzgen/rpzlib.py
RPZGen-0.1.4.dist-info/LICENSE
RPZGen-0.1.4.dist-info/METADATA
RPZGen-0.1.4.dist-info/WHEEL
RPZGen-0.1.4.dist-info/entry_points.txt
RPZGen-0.1.4.dist-info/top_level.txt
RPZGen-0.1.4.dist-info/RECORD
